TamilEnkal/TamilEnkal.py
TamilEnkal/__init__.py
TamilEnkal-1.0.0.dist-info/METADATA
TamilEnkal-1.0.0.dist-info/WHEEL
TamilEnkal-1.0.0.dist-info/top_level.txt
TamilEnkal-1.0.0.dist-info/RECORD
