Metadata-Version: 2.1
Name: TamilEnkal
Version: 1.0.0
Summary: A package for Tamil numeral operations.
Home-page: https://github.com/kathirkarky/TamilEnkal/
Author: Kathir Karky
Author-email: kathirkarky@gmail.com
License: MIT
Classifier: Development Status :: 5 - Production/Stable
Classifier: Intended Audience :: Developers
Classifier: License :: OSI Approved :: MIT License
Classifier: Operating System :: OS Independent
Classifier: Programming Language :: Python :: 3
